pyquickcopy/__init__.py
pyquickcopy/core.py
pyquickcopy-0.0.2.dist-info/LICENSE
pyquickcopy-0.0.2.dist-info/METADATA
pyquickcopy-0.0.2.dist-info/WHEEL
pyquickcopy-0.0.2.dist-info/top_level.txt
pyquickcopy-0.0.2.dist-info/RECORD
