Metadata-Version: 2.1
Name: pyquickcopy
Version: 0.0.2
Summary: Python implementation of [QuickCopy](https://github.com/foxe6/QuickCopy/). 
Home-page: https://github.com/foxe6/pyquickcopy
Author: f̣ộx̣ệ6
Author-email: foxe6@protonmail.com
License: AGPL-3.0
Keywords: quickcopy quick copy
Platform: UNKNOWN
Classifier: Programming Language :: Python :: 3.7
Classifier: Topic :: Utilities
Classifier: Natural Language :: English
Classifier: Intended Audience :: Developers
Classifier: License :: OSI Approved :: GNU Affero General Public License v3
Classifier: Operating System :: Microsoft :: Windows :: Windows 10
Requires-Python: >=3
Requires-Dist: pyperclip (>=0.0.1)
